retina_therm/__init__.py
retina_therm/cli.py
retina_therm/config.py
retina_therm/greens_functions.py
retina_therm/layers.py
retina_therm/multi_pulse_builder.py
retina_therm/parallel_jobs.py
retina_therm/progress_display.py
retina_therm/signals.py
retina_therm/units.py
retina_therm/utils.py
retina_therm/wasm/marcum_q.wasm
retina_therm-0.7.1.dist-info/METADATA
retina_therm-0.7.1.dist-info/WHEEL
retina_therm-0.7.1.dist-info/entry_points.txt
retina_therm-0.7.1.dist-info/RECORD
