Metadata-Version: 2.4
Name: retina-therm
Version: 0.7.1
Summary: A model for simulating retinal laser exposures.
Author-email: CD Clark III <clifton.clark@gmail.com>
Requires-Python: >=3.10
Requires-Dist: fspathtree>=1.0
Requires-Dist: h5py>=3.11.0
Requires-Dist: mpmath>=1.3.0
Requires-Dist: numpy>=2.1.1
Requires-Dist: pint>=0.24.3
Requires-Dist: powerconf>=0.7.0
Requires-Dist: pydantic>=2.9.2
Requires-Dist: pyyaml>=6.0.2
Requires-Dist: tissue-properties>=0.2.0
Requires-Dist: tqdm>=4.66.5
Requires-Dist: typer>=0.12.5
